Metadata-Version: 1.0
Name: aeveralltestingpypi
Version: 0.1
Summary: Test of PyPI
Home-page: UNKNOWN
Author: Andrew Everall
Author-email: andrew.everall1995@gmail.com
License: GPLv3
Platform: UNKNOWN
